object_api/__init__.py
object_api/app.py
object_api/entity.py
object_api/request_context.py
object_api/router_builder.py
object_api/service_builder.py
object_api/utils/dict_db.py
object_api/utils/has_post_init.py
object_api/utils/python.py
object_api/utils/session.py
object_api-0.0.1.dist-info/METADATA
object_api-0.0.1.dist-info/WHEEL
object_api-0.0.1.dist-info/RECORD
