Metadata-Version: 2.1
Name: object-api
Version: 0.0.1
Summary: 
Author: Jacob Valdez
Author-email: jacobfv123@gmail.com
Requires-Python: >=3.10,<4.0
Classifier: Programming Language :: Python :: 3
Classifier: Programming Language :: Python :: 3.10
Classifier: Programming Language :: Python :: 3.11
Requires-Dist: black (>=23.7.0,<24.0.0)
Requires-Dist: fastapi (>=0.101.0,<0.102.0)
Requires-Dist: httpx (>=0.24.1,<0.25.0)
Requires-Dist: inspect-mate-pp (>=0.0.4,<0.0.5)
Requires-Dist: pydantic (>=1.8.2,<2.0.0)
Requires-Dist: scheduler (>=0.8.4,<0.9.0)
Requires-Dist: sqlmodel (>=0.0.8,<0.0.9)
Requires-Dist: stringcase (>=1.2.0,<2.0.0)
